hp_tracker/__init__.py
hp_tracker/exceptions.py
hp_tracker/tracker.py
hp_tracker-0.0.2.dist-info/LICENSE
hp_tracker-0.0.2.dist-info/METADATA
hp_tracker-0.0.2.dist-info/WHEEL
hp_tracker-0.0.2.dist-info/top_level.txt
hp_tracker-0.0.2.dist-info/RECORD
