Metadata-Version: 2.1
Name: hp-tracker
Version: 0.0.2
Summary: Track posta.hr package status
Home-page: https://gitlab.com/vojko.pribudic/hp-tracker
Author: Vojko Pribudić
Author-email: dmanthing@gmail.com
License: UNKNOWN
Platform: UNKNOWN
Classifier: Programming Language :: Python :: 3
Classifier: License :: OSI Approved :: MIT License
Classifier: Operating System :: OS Independent
Requires-Python: >=3.6
Requires-Dist: bs4
Requires-Dist: requests
